{
  "work_id": "match_CZ3C_2024_md31_1755532333",
  "work_type": "match_data",
  "version": "2.1",
  "competition_id": "CZ3C",
  "competition_code": "ceska-fotbalova-liga",
  "competition_name": "CFL",
  "season_year": "2024",
  "target_matchday": {
    "number": 31,
    "expected_matches": 17,
    "existing_matches": 0,
    "status": "missing",
    "completion_reason": "not_discovered"
  },
  "team_count": 34,
  "expected_matchdays": 66,
  "priority": 178,
  "estimated_matches": 17,
  "processing_hints": {
    "matchday_focused": true,
    "single_matchday_target": 31,
    "expected_completion_time": "5_to_15_minutes",
    "team_count_category": "large",
    "scope": "targeted_matchday"
  },
  "created_at": "2025-08-18T18:52:13Z",
  "created_by": "matchday_targeted_work_manager",
  "status": "claimed",
  "claimed_by": "match_ASEs-MacBook-Pro.local_3541_72f5d5f5",
  "claimed_at": "2025-08-19T22:43:29.085730",
  "claim_id": "match_ASEs-MacBook-Pro.local_3541_72f5d5f5_1755632609085_f21a6b59"
}